agent_mcp_tools/__init__.py
agent_mcp_tools/__main__.py
agent_mcp_tools/config.py
agent_mcp_tools/core/__init__.py
agent_mcp_tools/core/executor.py
agent_mcp_tools/core/mcp_tool_manager.py
agent_mcp_tools/core/llm/__init__.py
agent_mcp_tools/core/llm/base.py
agent_mcp_tools/core/llm/factory.py
agent_mcp_tools/core/llm/openrouter.py
agent_mcp_tools/interfaces/__init__.py
agent_mcp_tools/interfaces/cli.py
agent_mcp_tools/interfaces/mcp_server.py
agent_mcp_tools-0.4.0.dist-info/licenses/LICENSE
agent_mcp_tools-0.4.0.dist-info/METADATA
agent_mcp_tools-0.4.0.dist-info/WHEEL
agent_mcp_tools-0.4.0.dist-info/entry_points.txt
agent_mcp_tools-0.4.0.dist-info/top_level.txt
agent_mcp_tools-0.4.0.dist-info/RECORD
