Metadata-Version: 2.4
Name: agent-mcp-tools
Version: 0.4.0
Summary: Agent MCP Tools - LLM agent framework using Model Context Protocol for multi-agent systems
Author-email: PsychArch <example@example.com>
License-Expression: MIT
Project-URL: Homepage, https://github.com/PsychArch/agent-mcp-tools
Project-URL: Bug Tracker, https://github.com/PsychArch/agent-mcp-tools/issues
Project-URL: Source Code, https://github.com/PsychArch/agent-mcp-tools
Classifier: Programming Language :: Python :: 3
Classifier: Programming Language :: Python :: 3.11
Classifier: Programming Language :: Python :: 3.12
Classifier: Programming Language :: Python :: 3.13
Classifier: Operating System :: OS Independent
Classifier: Development Status :: 4 - Beta
Classifier: Intended Audience :: Developers
Classifier: Intended Audience :: Science/Research
Classifier: Topic :: Scientific/Engineering :: Artificial Intelligence
Requires-Python: >=3.11
License-File: LICENSE
Requires-Dist: requests>=2.32.3
Requires-Dist: httpx>=0.28.1
Requires-Dist: typer>=0.15.4
Requires-Dist: mcp>=1.9.0
Requires-Dist: httpx-sse>=0.4.0
Requires-Dist: fastmcp>=2.10.2
Requires-Dist: rich>=14.0.0
Dynamic: license-file
